pyscca.cp38-win_amd64.pyd
libscca_python-20250915.dist-info/COPYING
libscca_python-20250915.dist-info/COPYING.LESSER
libscca_python-20250915.dist-info/METADATA
libscca_python-20250915.dist-info/WHEEL
libscca_python-20250915.dist-info/top_level.txt
libscca_python-20250915.dist-info/RECORD
